<?xml version='1.0' encoding='UTF-8'?>
<object id="6Y4uP8mrsdxQ" classes="section" acceptedChildren=":Proteus-any" acceptedParents=":Proteus-document section">
  <properties>
    <stringProperty name=":Proteus-name" category="general"><![CDATA[Descripción de actores de negocio actuales]]></stringProperty>
    <markdownProperty name="comments" category="general"><![CDATA[]]></markdownProperty>
  </properties>
  <children>
    <child id="6x5WZ3T3GXY9"/>
    <child id="4AG3MmTrezpx"/>
    <child id="7MuwCSTgqny6"/>
    <child id="4fXgvxG9BJAc"/>
    <child id="7e3sSziicsPw"/>
    <child id="6NzMYZDjvSEL"/>
    <child id="5EaeUWKCKbdz"/>
  </children>
</object>
